sindri/__init__.py
sindri/cli/__init__.py
sindri/cli/app.py
sindri/cli/commands.py
sindri/cli/display.py
sindri/cli/interactive_init.py
sindri/cli/main.py
sindri/cli/parsing.py
sindri/cli/subcommands.py
sindri/cli/template.py
sindri/commands/__init__.py
sindri/commands/command.py
sindri/commands/group.py
sindri/commands/shell_command.py
sindri/commands/application/__init__.py
sindri/commands/application/application_group.py
sindri/commands/application/commands/__init__.py
sindri/commands/application/commands/build.py
sindri/commands/application/commands/re.py
sindri/commands/application/commands/restart.py
sindri/commands/application/commands/start.py
sindri/commands/application/commands/stop.py
sindri/commands/compose/__init__.py
sindri/commands/compose/compose_group.py
sindri/commands/docker/__init__.py
sindri/commands/docker/docker_group.py
sindri/commands/general/__init__.py
sindri/commands/general/general_group.py
sindri/commands/general/commands/__init__.py
sindri/commands/general/commands/install.py
sindri/commands/general/commands/setup.py
sindri/commands/general/commands/version.py
sindri/commands/git/__init__.py
sindri/commands/git/git_group.py
sindri/commands/pypi/__init__.py
sindri/commands/pypi/pypi_group.py
sindri/commands/pypi/commands/__init__.py
sindri/commands/pypi/commands/push.py
sindri/commands/pypi/commands/validate.py
sindri/commands/quality/__init__.py
sindri/commands/quality/quality_group.py
sindri/commands/quality/commands/__init__.py
sindri/commands/quality/commands/cov.py
sindri/commands/quality/commands/lint.py
sindri/commands/quality/commands/test.py
sindri/commands/quality/commands/validate.py
sindri/commands/sindri/__init__.py
sindri/commands/sindri/sindri_group.py
sindri/commands/sindri/commands/__init__.py
sindri/commands/version/__init__.py
sindri/commands/version/version_group.py
sindri/commands/version/commands/__init__.py
sindri/commands/version/commands/bump.py
sindri/commands/version/commands/show.py
sindri_dev-0.1.2.dist-info/METADATA
sindri_dev-0.1.2.dist-info/WHEEL
sindri_dev-0.1.2.dist-info/entry_points.txt
sindri_dev-0.1.2.dist-info/licenses/LICENSE
sindri_dev-0.1.2.dist-info/RECORD
