Metadata-Version: 2.4
Name: sindri-dev
Version: 0.1.2
Summary: A project-configurable command palette for common dev workflows
Project-URL: Homepage, https://github.com/yourusername/sindri
Project-URL: Documentation, https://github.com/yourusername/sindri#readme
Project-URL: Repository, https://github.com/yourusername/sindri
Project-URL: Issues, https://github.com/yourusername/sindri/issues
Author: Sindri Contributors
License: MIT
License-File: LICENSE
Keywords: cli,command-palette,dev-tools,workflow
Classifier: Development Status :: 3 - Alpha
Classifier: Intended Audience :: Developers
Classifier: License :: OSI Approved :: MIT License
Classifier: Programming Language :: Python :: 3
Classifier: Programming Language :: Python :: 3.11
Classifier: Programming Language :: Python :: 3.12
Classifier: Programming Language :: Python :: 3.13
Requires-Python: >=3.11
Requires-Dist: pydantic>=2.0.0
Requires-Dist: rich>=13.0.0
Requires-Dist: structlog>=24.0.0
Requires-Dist: typer>=0.9.0
Provides-Extra: all
Requires-Dist: build>=1.0.0; extra == 'all'
Requires-Dist: twine>=5.0.0; extra == 'all'
Provides-Extra: compose
Provides-Extra: dev
Requires-Dist: pytest-asyncio>=0.21.0; extra == 'dev'
Requires-Dist: pytest-cov>=4.0.0; extra == 'dev'
Requires-Dist: pytest>=7.0.0; extra == 'dev'
Provides-Extra: docker
Provides-Extra: docker-all
Provides-Extra: git
Provides-Extra: pypi
Requires-Dist: build>=1.0.0; extra == 'pypi'
Requires-Dist: twine>=5.0.0; extra == 'pypi'
Provides-Extra: version
